{
  "blockModel": {
    "gridSize": 1,
    "origin": [0, 0, 0],
    "chunk": [
      [-4, 0, -3, 15894850],
      [-4, 0, -2, 15894850],
      [-4, 0, -1, 15894850],
      [-3, 0, -2, 15894850],
      [-2, 0, -3, 15894850],
      [-2, 0, -2, 15894850],
      [-2, 0, -1, 15894850],
      [-1, 0, -3, 15894850],
      [-1, 0, -2, 15894850],
      [-1, 0, -1, 15894850],
      [-4, 0, 0, 15894850],
      [-2, 0, 0, 15894850],
      [-2, 0, 1, 15894850],
      [-1, 0, 0, 16185078],
      [-1, 0, 1, 15894850],
      [-1, 0, 2, 15894850],
      [-1, 0, 3, 15894850],
      [0, 0, -3, 15894850],
      [0, 0, -2, 15894850],
      [0, 0, -1, 15894850],
      [1, 0, -2, 15894850],
      [2, 0, -3, 15894850],
      [2, 0, -2, 15894850],
      [2, 0, -1, 15894850],
      [0, 0, 0, 15894850],
      [0, 0, 1, 15894850],
      [2, 0, 0, 15894850]
    ]
  },
  "blockAttachments": [{
    "coord": {
      "x": -4,
      "y": 0,
      "z": -3
    },
    "type": "engine"
  }, {
    "coord": {
      "x": 2,
      "y": 0,
      "z": -3
    },
    "type": "engine"
  }, {
    "coord": {
      "x": -4,
      "y": 0,
      "z": 0
    },
    "type": "laser"
  }, {
    "coord": {
      "x": 2,
      "y": 0,
      "z": 0
    },
    "type": "laser"
  }]
}